pangea/__init__.py
pangea/audit_logger.py
pangea/config.py
pangea/deep_verify.py
pangea/dump_audit.py
pangea/exceptions.py
pangea/request.py
pangea/response.py
pangea/services/__init__.py
pangea/services/audit/audit.py
pangea/services/audit/exceptions.py
pangea/services/audit/models.py
pangea/services/audit/signing.py
pangea/services/audit/util.py
pangea/services/base.py
pangea/services/embargo.py
pangea/services/intel.py
pangea/services/redact.py
pangea/services/secrets.py
pangea/tools_util.py
pangea/verify.py
python_pangea-0.3.2.dist-info/WHEEL
python_pangea-0.3.2.dist-info/METADATA
python_pangea-0.3.2.dist-info/RECORD
