Metadata-Version: 2.1
Name: python-pangea
Version: 0.3.2
Summary: Pangea API SDK
License: MIT
Keywords: Pangea,SDK,Audit
Author: Glenn Gallien
Author-email: glenn.gallien@pangea.cloud
Requires-Python: >=3.7.2,<4.0.0
Classifier: License :: OSI Approved :: MIT License
Classifier: Programming Language :: Python :: 3
Classifier: Programming Language :: Python :: 3.8
Classifier: Programming Language :: Python :: 3.9
Classifier: Programming Language :: Python :: 3.10
Classifier: Programming Language :: Python :: 3.11
Classifier: Topic :: Software Development
Classifier: Topic :: Software Development :: Libraries
Requires-Dist: alive-progress (>=2.4.1,<3.0.0)
Requires-Dist: cryptography (==37.0.2)
Requires-Dist: pydantic (>=1.10.2,<2.0.0)
Requires-Dist: python-dateutil (>=2.8.2,<3.0.0)
Requires-Dist: requests (>=2.27.1,<3.0.0)
Requires-Dist: schema (>=0.7.5,<0.8.0)
